aws_session/__init__.py
aws_session/__main__.py
aws_session-5.5.0.dist-info/METADATA
aws_session-5.5.0.dist-info/WHEEL
aws_session-5.5.0.dist-info/entry_points.txt
aws_session-5.5.0.dist-info/top_level.txt
aws_session-5.5.0.dist-info/RECORD
