Metadata-Version: 2.1
Name: aws-session
Version: 5.5.0
Summary: A CLI to generate session credentials based on ~/.aws/config profiles and store them as profile in ~/.aws/credentials file
Home-page: https://github.com/qoomon/aws-session
Author: Bengt Brodersen
Author-email: me@qoomon.me
License: UNKNOWN
Platform: UNKNOWN
Classifier: Development Status :: 5 - Production/Stable
Classifier: License :: OSI Approved :: MIT License
Classifier: Operating System :: OS Independent
Classifier: Environment :: Console
Classifier: Programming Language :: Python :: 3
Classifier: Programming Language :: Python :: 3.5
Classifier: Programming Language :: Python :: 3.6
Classifier: Programming Language :: Python :: 3.7
Classifier: Programming Language :: Python :: 3.8
Classifier: Programming Language :: Python :: 3.9
Classifier: Topic :: System :: Systems Administration
Classifier: Intended Audience :: Developers
Classifier: Intended Audience :: System Administrators
Requires-Dist: botocore (<2,>=1.16.0)
